{"version":2,"baseVals":{"rating":5,"gammaadj":2.7,"wave_mode":3,"wave_a":4.1,"wave_scale":2.246,"wave_smoothing":0.7,"warpscale":1.331,"zoom":1.01299,"warp":0.00016,"sx":0.99967,"sy":0.9999,"wave_g":0.65,"wave_b":0.25,"wave_y":0.38,"mv_a":0},"shapes":[{"baseVals":{"enabled":0},"init_eqs_str":"","frame_eqs_str":"","init_eqs_eel":"","frame_eqs_eel":""},{"baseVals":{"enabled":0},"init_eqs_str":"","frame_eqs_str":"","init_eqs_eel":"","frame_eqs_eel":""},{"baseVals":{"enabled":0},"init_eqs_str":"","frame_eqs_str":"","init_eqs_eel":"","frame_eqs_eel":""},{"baseVals":{"enabled":0},"init_eqs_str":"","frame_eqs_str":"","init_eqs_eel":"","frame_eqs_eel":""}],"waves":[{"baseVals":{"enabled":0},"init_eqs_str":"","frame_eqs_str":"","point_eqs_str":"","init_eqs_eel":"","frame_eqs_eel":"","point_eqs_eel":""},{"baseVals":{"enabled":0},"init_eqs_str":"","frame_eqs_str":"","point_eqs_str":"","init_eqs_eel":"","frame_eqs_eel":"","point_eqs_eel":""},{"baseVals":{"enabled":0},"init_eqs_str":"","frame_eqs_str":"","point_eqs_str":"","init_eqs_eel":"","frame_eqs_eel":"","point_eqs_eel":""},{"baseVals":{"enabled":0},"init_eqs_str":"","frame_eqs_str":"","point_eqs_str":"","init_eqs_eel":"","frame_eqs_eel":"","point_eqs_eel":""}],"init_eqs_str":"a.du=0;a.q1=0;a.mult=0;a.ang2=0;a.dv=0;a.q4=0;a.q2=0;a.dist=0;a.q3=0;","frame_eqs_str":"a.wave_r+=.25*(.6*Math.sin(.98*a.time)+.4*Math.sin(1.047*a.time));a.wave_g+=.25*(.6*Math.sin(.835*a.time)+.4*Math.sin(1.081*a.time));a.wave_b+=.25*(.6*Math.sin(.814*a.time)+.4*Math.sin(1.011*a.time));a.q1=2*a.cx-1+.92*(.6*Math.sin(.374*a.time)+.4*Math.sin(.494*a.time));a.q2=2*a.cy-1+.92*(.6*Math.sin(.393*a.time)+.4*Math.sin(.423*a.time));a.q3=2*a.cx-1+.92*(.6*Math.sin(.174*-a.time)+.4*Math.sin(.364*a.time));a.q4=2*a.cy-1+.92*(.6*Math.sin(.234*a.time)+.4*Math.sin(.271*-a.time));\n","pixel_eqs_str":"a.du=2*a.x-1-a.q1;a.dv=2*a.y-1-a.q2;a.dist=sqrt(a.du*a.du+a.dv*a.dv);a.ang2=Math.atan2(a.du,a.dv);a.mult=div(.012,a.dist+.4);a.dx=a.mult*Math.sin(a.ang2-1.5);a.dy=a.mult*Math.cos(a.ang2-1.5);a.du=2*a.x-1-a.q3;a.dv=2*a.y-1-a.q4;a.dist=sqrt(a.du*a.du+a.dv*a.dv);a.ang2=Math.atan2(a.du,a.dv);a.mult=div(.012,a.dist+.4);a.dx+=a.mult*Math.sin(a.ang2+1.5);a.dy+=a.mult*Math.cos(a.ang2+1.5);","init_eqs_eel":"","frame_eqs_eel":"wave_r = wave_r + 0.250*( 0.60*sin(0.980*time) + 0.40*sin(1.047*time) );\nwave_g = wave_g + 0.250*( 0.60*sin(0.835*time) + 0.40*sin(1.081*time) );\nwave_b = wave_b + 0.250*( 0.60*sin(0.814*time) + 0.40*sin(1.011*time) );\nq1 = (cx*2-1) + 0.92*( 0.60*sin(0.374*time) + 0.40*sin(0.494*time) );\nq2 = (cy*2-1) + 0.92*( 0.60*sin(0.393*time) + 0.40*sin(0.423*time) );\nq3 = (cx*2-1) + 0.92*( 0.60*sin(0.174*-time) + 0.40*sin(0.364*time) );\nq4 = (cy*2-1) + 0.92*( 0.60*sin(0.234*time) + 0.40*sin(0.271*-time) );","pixel_eqs_eel":"du = (x*2-1) - q1;\ndv = (y*2-1) - q2;\ndist = sqrt(du*du+dv*dv);\nang2 = atan2(du,dv);\nmult = 0.012/(dist+0.4);\ndx = mult*sin(ang2-1.5);\ndy = mult*cos(ang2-1.5);\ndu = (x*2-1) - q3;\ndv = (y*2-1) - q4;\ndist = sqrt(du*du+dv*dv);\nang2 = atan2(du,dv);\nmult = 0.012/(dist+0.4);\ndx = dx + mult*sin(ang2+1.5);\ndy = dy + mult*cos(ang2+1.5);","warp":"vec3 xlat_mutablemus;\n shader_body { \n  vec3 crisp_1;\n  vec2 uv6_2;\n  vec2 tmpvar_3;\n  tmpvar_3 = (uv - 0.5);\n  float tmpvar_4;\n  tmpvar_4 = (dot (texture (sampler_noise_hq, (uv / 4.0)), vec4(0.32, 0.49, 0.29, 0.0)) * q31);\n  mat2 tmpvar_5;\n  tmpvar_5[uint(0)].x = cos(tmpvar_4);\n  tmpvar_5[uint(0)].y = sin(tmpvar_4);\n  tmpvar_5[1u].x = -(sin(tmpvar_4));\n  tmpvar_5[1u].y = cos(tmpvar_4);\n  uv6_2 = (tmpvar_3 * tmpvar_5);\n  uv6_2 = (uv6_2 + sin((q32 * tmpvar_3)));\n  xlat_mutablemus = (vec3((0.2 / (\n    sqrt(uv6_2.x)\n   + 0.2))) * vec3(1.1, 1.0, 0.95));\n  xlat_mutablemus = (xlat_mutablemus * (0.9 + (0.1 * texture (sampler_noise_hq, uv))).xyz);\n  vec3 tmpvar_6;\n  tmpvar_6 = ((texture (sampler_blur1, fract(uv)).xyz * scale1) + bias1);\n  vec2 tmpvar_7;\n  tmpvar_7.x = dot ((texture (sampler_main, (uv + vec2(0.005, 0.0))) - texture (sampler_main, (uv - vec2(0.005, 0.0)))), vec4(0.32, 0.49, 0.29, 0.0));\n  tmpvar_7.y = dot ((texture (sampler_main, (uv + vec2(0.0, 0.005))) - texture (sampler_main, (uv - vec2(0.0, 0.005)))), vec4(0.32, 0.49, 0.29, 0.0));\n  crisp_1 = (texture (sampler_main, (uv + (tmpvar_7 * 0.02))).xyz + (texture (sampler_main, uv).xyz / 2.0));\n  crisp_1 = (crisp_1 * 0.67);\n  crisp_1 = (crisp_1 + ((0.08 * xlat_mutablemus) - (\n    sqrt(dot (tmpvar_7, tmpvar_7))\n   * tmpvar_6)));\n  vec4 tmpvar_8;\n  tmpvar_8.w = 1.0;\n  tmpvar_8.xyz = (((crisp_1 - \n    (dot (tmpvar_6, vec3(0.32, 0.49, 0.29)) * 0.04)\n  ) * 0.99) - 0.04);\n  ret = tmpvar_8.xyz;\n }","comp":"","warp_hlsl":"float3 color, mus;\nfloat dx,dy;\n\nshader_body {\nfloat corr = texsize.xy*texsize_noise_lq.zw;\n\nfloat2 uv1 = (uv-.5);\nfloat2 uv6 = uv1;\n\nfloat rota = lum(tex2D (sampler_noise_hq,uv/4))*q31;\n\nuv6 = mul(uv1,float2x2(cos(rota),-sin(rota),sin(rota),cos(rota)));\nuv6 += sin(q32*uv1);\nmus = .2/(sqrt(uv6.x)+.2);\n\nmus *= float3 (1.1,1,.95);\nmus *= .9+.1*tex2D (sampler_noise_hq,uv);\n\nfloat3 blur = GetBlur1(frac(uv));\n\nfloat2 hor = float2 (0.005,0);\nfloat2 ver = float2 (0,.005);\n\nfloat dx = lum(tex2D(sampler_main,uv+hor) \n         - tex2D(sampler_main,uv-hor));\nfloat dy = lum(tex2D(sampler_main,uv+ver) \n         - tex2D(sampler_main,uv-ver));\n\n\nfloat2 zz = float2 (dx,dy);\n\nfloat3 crisp= tex2D(sampler_main,uv+zz*.02);\nfloat3 crisp2 = tex2D(sampler_main,uv);\ncrisp += crisp2/2;\ncrisp *= .67;\ncrisp +=.08 * mus - length(zz)*blur;\n\nfloat3 ret1 = crisp - lum(blur)*.04;\nret = ret1 * .99 -  .04 ;\n}","comp_hlsl":""}