{"version":2,"baseVals":{"rating":1,"gammaadj":1.28,"decay":1,"echo_zoom":1,"echo_alpha":0.5,"echo_orient":3,"wave_mode":7,"additivewave":1,"modwavealphabyvolume":1,"wave_brighten":0,"wave_a":0.001,"wave_scale":1.286,"wave_smoothing":0.63,"modwavealphastart":0.71,"modwavealphaend":1.3,"warpanimspeed":2.599,"warpscale":0.01,"zoomexp":0.9999,"fshader":1,"zoom":0.9996,"warp":0.01,"sy":1.0017,"wave_r":0.65,"wave_g":0.65,"wave_b":0.65,"ob_size":0,"ob_r":1,"ob_g":1,"ob_b":1,"ib_size":0.075,"ib_r":0,"ib_g":0,"ib_b":0,"ib_a":1,"mv_x":64,"mv_y":48,"mv_l":0,"mv_a":0},"shapes":[{"baseVals":{"textured":1,"rad":1.79142,"tex_ang":0.62832,"g":1,"b":1,"a":0,"g2":0,"a2":1,"border_a":0,"enabled":0},"init_eqs_str":"","frame_eqs_str":"","init_eqs_eel":"","frame_eqs_eel":""},{"baseVals":{"enabled":0},"init_eqs_str":"","frame_eqs_str":"","init_eqs_eel":"","frame_eqs_eel":""},{"baseVals":{"enabled":0},"init_eqs_str":"","frame_eqs_str":"","init_eqs_eel":"","frame_eqs_eel":""},{"baseVals":{"enabled":0},"init_eqs_str":"","frame_eqs_str":"","init_eqs_eel":"","frame_eqs_eel":""}],"waves":[{"baseVals":{"enabled":1,"thick":1},"init_eqs_str":"a.ma=0;a.mx=0;a.my=0;a.pi23=0;a.vol=0;","frame_eqs_str":"","point_eqs_str":"a.ma+=3.1415*above(a.bass,1)*.01*a.bass;a.ma-=3.1415*above(a.treb,1)*.01*a.treb;a.mx+=.0002*Math.cos(a.ma);a.my+=.0002*Math.sin(a.ma);a.mx=.00001<Math.abs(above(a.mx,.9))?.9-a.mx:a.mx;a.my=.00001<Math.abs(above(a.my,.9))?.9-a.my:a.my;a.mx=.00001<Math.abs(below(a.mx,.1))?.9+a.mx:a.mx;a.my=.00001<Math.abs(below(a.my,.1))?.9+a.my:a.my;a.x=a.mx;a.y=a.my;a.a=above(a.bass+a.mid+a.treb,.8);a.pi23=1.333333332*Math.asin(1);a.vol=a.bass+a.mid+a.treb;a.r=.5*(Math.sin(.3*a.time+a.vol-0*\na.pi23)+1);a.g=.5*(Math.sin(.3*a.time+a.vol-1*a.pi23)+1);a.b=.5*(Math.sin(.3*a.time+a.vol-2*a.pi23)+1);","init_eqs_eel":"","frame_eqs_eel":"","point_eqs_eel":"ma=ma+(above(bass,1)*3.1415*.01*bass);\nma=ma-(above(treb,1)*3.1415*.01*treb);\n\nmx=mx+(.0002*cos(ma));\nmy=my+(.0002*sin(ma));\n\nmx=if(above(mx,.9),(.9-mx),mx);\nmy=if(above(my,.9),(.9-my),my);\nmx=if(below(mx,.1),(.9+mx),mx);\nmy=if(below(my,.1),(.9+my),my);\n\nx=mx;\ny=my;\n\na=(above(bass+mid+treb,.8));\npi23=4*asin(1)*.333333333;\nvol=bass+mid+treb;\nr=(sin(time*.3+vol-0*pi23)+1)*.5;\ng=(sin(time*.3+vol-1*pi23)+1)*.5;\nb=(sin(time*.3+vol-2*pi23)+1)*.5;"},{"baseVals":{"enabled":1,"thick":1},"init_eqs_str":"a.ma=0;a.mx=0;a.my=0;a.pi23=0;a.vol=0;","frame_eqs_str":"","point_eqs_str":"a.ma+=3.1415*above(a.bass,1)*.05*a.bass;a.ma-=3.1415*above(a.mid,1)*.05*a.mid;a.mx+=.0001*Math.cos(a.ma);a.my+=.0001*Math.sin(a.ma);a.mx=.00001<Math.abs(above(a.mx,.9))?.9-a.mx:a.mx;a.my=.00001<Math.abs(above(a.my,.9))?.9-a.my:a.my;a.mx=.00001<Math.abs(below(a.mx,.1))?.9+a.mx:a.mx;a.my=.00001<Math.abs(below(a.my,.1))?.9+a.my:a.my;a.x=a.mx;a.y=a.my;a.a=above(a.bass+a.mid+a.treb,.1);a.pi23=1.333333332*Math.asin(1);a.vol=a.bass+a.mid+a.treb;a.r=.5*(Math.sin(.3*a.time+a.vol-0*a.pi23)+\n1);a.g=.5*(Math.sin(.3*a.time+a.vol-1*a.pi23)+1);a.b=.5*(Math.sin(.3*a.time+a.vol-2*a.pi23)+1);","init_eqs_eel":"","frame_eqs_eel":"","point_eqs_eel":"ma=ma+(above(bass,1)*3.1415*.05*bass);\nma=ma-(above(mid,1)*3.1415*.05*mid);\n\nmx=mx+(.0001*cos(ma));\nmy=my+(.0001*sin(ma));\n\nmx=if(above(mx,.9),(.9-mx),mx);\nmy=if(above(my,.9),(.9-my),my);\nmx=if(below(mx,.1),(.9+mx),mx);\nmy=if(below(my,.1),(.9+my),my);\n\nx=mx;\ny=my;\n\na=(above(bass+mid+treb,.1));\npi23=4*asin(1)*.333333333;\nvol=bass+mid+treb;\nr=(sin(time*.3+vol-0*pi23)+1)*.5;\ng=(sin(time*.3+vol-1*pi23)+1)*.5;\nb=(sin(time*.3+vol-2*pi23)+1)*.5;"},{"baseVals":{"enabled":1,"usedots":1,"thick":1},"init_eqs_str":"a.ma=0;a.mx=0;a.my=0;a.pi23=0;a.vol=0;","frame_eqs_str":"","point_eqs_str":"a.ma+=3.1415*above(a.mid,1)*.01*a.mid;a.ma-=3.1415*above(a.treb,1)*.01*a.treb;a.mx+=.0004*Math.cos(a.ma);a.my+=.0004*Math.sin(a.ma);a.mx=.00001<Math.abs(above(a.mx,.9))?.9-a.mx:a.mx;a.my=.00001<Math.abs(above(a.my,.9))?.9-a.my:a.my;a.mx=.00001<Math.abs(below(a.mx,.1))?.9+a.mx:a.mx;a.my=.00001<Math.abs(below(a.my,.1))?.9+a.my:a.my;a.x=a.mx;a.y=a.my;a.a=above(a.bass+a.mid+a.treb,.3);a.pi23=1.333333332*Math.asin(1);a.vol=a.bass+a.mid+a.treb;a.r=.5*(Math.sin(.3*a.time+a.vol-0*a.pi23)+\n1);a.g=.5*(Math.sin(.3*a.time+a.vol-1*a.pi23)+1);a.b=.5*(Math.sin(.3*a.time+a.vol-2*a.pi23)+1);","init_eqs_eel":"","frame_eqs_eel":"","point_eqs_eel":"ma=ma+(above(mid,1)*3.1415*.01*mid);\nma=ma-(above(treb,1)*3.1415*.01*treb);\n\nmx=mx+(.0004*cos(ma));\nmy=my+(.0004*sin(ma));\n\nmx=if(above(mx,.9),(.9-mx),mx);\nmy=if(above(my,.9),(.9-my),my);\nmx=if(below(mx,.1),(.9+mx),mx);\nmy=if(below(my,.1),(.9+my),my);\n\nx=mx;\ny=my;\n\na=(above(bass+mid+treb,.3));\npi23=4*asin(1)*.333333333;\nvol=bass+mid+treb;\nr=(sin(time*.3+vol-0*pi23)+1)*.5;\ng=(sin(time*.3+vol-1*pi23)+1)*.5;\nb=(sin(time*.3+vol-2*pi23)+1)*.5;"},{"baseVals":{"enabled":1,"thick":1},"init_eqs_str":"a.ma=0;a.mx=0;a.my=0;a.pi23=0;a.vol=0;","frame_eqs_str":"","point_eqs_str":"a.ma+=3.1415*above(a.bass,.5)*.02*a.bass;a.ma-=3.1415*above(a.treb,.5)*.02*a.treb;a.mx+=.0008*Math.cos(a.ma);a.my+=.0008*Math.sin(a.ma);a.mx=.00001<Math.abs(above(a.mx,.9))?.9-a.mx:a.mx;a.my=.00001<Math.abs(above(a.my,.9))?.9-a.my:a.my;a.mx=.00001<Math.abs(below(a.mx,.1))?.9+a.mx:a.mx;a.my=.00001<Math.abs(below(a.my,.1))?.9+a.my:a.my;a.x=a.mx;a.y=a.my;a.a=above(a.bass+a.mid+a.treb,.2);a.pi23=1.333333332*Math.asin(1);a.vol=a.bass+a.mid+a.treb;a.r=.5*(Math.sin(.3*a.time+a.vol-\n0*a.pi23)+1);a.g=.5*(Math.sin(.3*a.time+a.vol-1*a.pi23)+1);a.b=.5*(Math.sin(.3*a.time+a.vol-2*a.pi23)+1);","init_eqs_eel":"","frame_eqs_eel":"","point_eqs_eel":"ma=ma+(above(bass,.5)*3.1415*.02*bass);\nma=ma-(above(treb,.5)*3.1415*.02*treb);\n\nmx=mx+(.0008*cos(ma));\nmy=my+(.0008*sin(ma));\n\nmx=if(above(mx,.9),(.9-mx),mx);\nmy=if(above(my,.9),(.9-my),my);\nmx=if(below(mx,.1),(.9+mx),mx);\nmy=if(below(my,.1),(.9+my),my);\n\nx=mx;\ny=my;\n\na=(above(bass+mid+treb,.2));\npi23=4*asin(1)*.333333333;\nvol=bass+mid+treb;\nr=(sin(time*.3+vol-0*pi23)+1)*.5;\ng=(sin(time*.3+vol-1*pi23)+1)*.5;\nb=(sin(time*.3+vol-2*pi23)+1)*.5;"}],"init_eqs_str":"a.q25=0;a.q12=0;a.redsine=0;a.q18=0;a.q22=0;a.q21=0;a.vt=0;a.bluesine=0;a.q13=0;a.q15=0;a.q29=0;a.q6=0;a.greenif=0;a.q1=0;a.q5=0;a.vb=0;a.q9=0;a.q31=0;a.q23=0;a.q24=0;a.q11=0;a.q10=0;a.q4=0;a.redif=0;a.blueif=0;a.q16=0;a.q26=0;a.q19=0;a.q17=0;a.vol=0;a.greensine=0;a.q2=0;a.q27=0;a.q14=0;a.q3=0;a.vvm=0;a.q32=0;a.vvb=0;a.q7=0;a.q28=0;a.vm=0;a.q30=0;a.q20=0;a.vvt=0;a.q8=0;a.decay=.1;","frame_eqs_str":"a.vb=.95*a.vb+(1-a.vb)*pow(a.bass_att,2)*.02;a.vvb=.95*a.vvb+(1-a.vvb)*a.vb*.01;a.vm=.95*a.vm+(1-a.vm)*pow(a.mid_att,2)*.02;a.vvm=.95*a.vvm+(1-a.vvm)*a.vm*.01;a.vt=.95*a.vt+(1-a.vt)*pow(a.treb_att,2)*.02;a.vvt=.95*a.vvt+(1-a.vvt)*a.vt*.01;a.vvb=Math.min(1,Math.max(0,a.vvb));a.vvm=Math.min(1,Math.max(0,a.vvm));a.vvt=Math.min(1,Math.max(0,a.vvt));a.q1=10*(a.vvb+a.vvm+a.vvt);a.q2=10*(a.vvb+a.vvm+a.vvt);a.q3=10*(a.vvb+a.vvm+a.vvt);a.q4=10*(a.vvb+a.vvm+a.vvt);a.q5=10*(a.vvb+a.vvm+\na.vvt);a.q6=10*(a.vvb+a.vvm+a.vvt);a.q7=10*(a.vvb+a.vvm+a.vvt);a.q8=10*(a.vvb+a.vvm+a.vvt);a.q9=10*(a.vvb+a.vvm+a.vvt);a.q10=10*(a.vvb+a.vvm+a.vvt);a.q11=10*(a.vvb+a.vvm+a.vvt);a.q12=10*(a.vvb+a.vvm+a.vvt);a.q13=10*(a.vvb+a.vvm+a.vvt);a.q14=10*(a.vvb+a.vvm+a.vvt);a.q15=10*(a.vvb+a.vvm+a.vvt);a.q16=10*(a.vvb+a.vvm+a.vvt);a.q17=10*(a.vvb+a.vvm+a.vvt);a.q18=10*(a.vvb+a.vvm+a.vvt);a.q19=10*(a.vvb+a.vvm+a.vvt);a.q20=10*(a.vvb+a.vvm+a.vvt);a.q21=10*(a.vvb+a.vvm+a.vvt);a.q22=10*(a.vvb+a.vvm+a.vvt);a.q23=\n10*(a.vvb+a.vvm+a.vvt);a.q24=10*(a.vvb+a.vvm+a.vvt);a.q25=10*(a.vvb+a.vvm+a.vvt);a.q26=10*(a.vvb+a.vvm+a.vvt);a.q27=10*(a.vvb+a.vvm+a.vvt);a.q28=10*(a.vvb+a.vvm+a.vvt);a.q29=10*(a.vvb+a.vvm+a.vvt);a.q30=10*(a.vvb+a.vvm+a.vvt);a.q31=10*(a.vvb+a.vvm+a.vvt);a.q32=10*(a.vvb+a.vvm+a.vvt);a.vol=.3333*(a.bass+a.mid+a.treb_att);a.redsine=.5+.15*a.bass*Math.sin(3*a.time);a.greensine=.5+.15*a.mid*Math.sin(2*a.time);a.bluesine=.5+.15*a.treb*Math.sin(a.time);a.redif=.00001<Math.abs(above(a.bass,1.2))?a.redsine:\n.00001<Math.abs(above(a.redif,.95))?0:.85*a.redif;a.greenif=.00001<Math.abs(above(a.mid,1.2))?a.greensine:.00001<Math.abs(above(a.greenif,.95))?0:.85*a.greenif;a.blueif=.00001<Math.abs(above(a.treb,1.2))?a.bluesine:.00001<Math.abs(above(a.blueif,.95))?0:.85*a.blueif;a.wave_r=a.redif;a.wave_g=a.greenif;a.wave_b=a.blueif;a.q11=Math.sin(a.time)-1;a.q12=Math.sin(a.time)-1;","pixel_eqs_str":"a.dx+=.08*Math.sin(32*a.x+20*Math.sin(.51*a.time)*Math.cos(.41*a.time));a.dy+=.08*Math.sin(32*a.y+20*Math.sin(.58*a.time)*Math.cos(.33*a.time));","init_eqs_eel":"decay=0.1;","frame_eqs_eel":"//per frame less reactive volume for all unused q vars, put before other q vars are set for cop out mashing\nvb = vb*0.95 + (1-vb)*pow(bass_att,2)*0.02;\nvvb = vvb*0.95 + (1-vvb)*vb*0.01;\nvm = vm*0.95 + (1-vm)*pow(mid_att,2)*0.02;\nvvm = vvm*0.95 + (1-vvm)*vm*0.01;\nvt = vt*0.95 + (1-vt)*pow(treb_att,2)*0.02;\nvvt = vvt*0.95 + (1-vvt)*vt*0.01;\nvvb = min(1,max(0,vvb));\nvvm = min(1,max(0,vvm));\nvvt = min(1,max(0,vvt));\nq1   = (vvb+vvm+vvt)*10;\nq2   = (vvb+vvm+vvt)*10;\nq3   = (vvb+vvm+vvt)*10;\nq4   = (vvb+vvm+vvt)*10;\nq5   = (vvb+vvm+vvt)*10;\nq6   = (vvb+vvm+vvt)*10;\nq7   = (vvb+vvm+vvt)*10;\nq8   = (vvb+vvm+vvt)*10;\nq9   = (vvb+vvm+vvt)*10;\nq10  = (vvb+vvm+vvt)*10;\nq11  = (vvb+vvm+vvt)*10;\nq12  = (vvb+vvm+vvt)*10;\nq13  = (vvb+vvm+vvt)*10;\nq14  = (vvb+vvm+vvt)*10;\nq15  = (vvb+vvm+vvt)*10;\nq16  = (vvb+vvm+vvt)*10;\nq17  = (vvb+vvm+vvt)*10;\nq18  = (vvb+vvm+vvt)*10;\nq19  = (vvb+vvm+vvt)*10;\nq20  = (vvb+vvm+vvt)*10;\nq21  = (vvb+vvm+vvt)*10;\nq22  = (vvb+vvm+vvt)*10;\nq23  = (vvb+vvm+vvt)*10;\nq24  = (vvb+vvm+vvt)*10;\nq25  = (vvb+vvm+vvt)*10;\nq26  = (vvb+vvm+vvt)*10;\nq27  = (vvb+vvm+vvt)*10;\nq28  = (vvb+vvm+vvt)*10;\nq29  = (vvb+vvm+vvt)*10;\nq30  = (vvb+vvm+vvt)*10;\nq31  = (vvb+vvm+vvt)*10;\nq32  = (vvb+vvm+vvt)*10;\n\n\n\nvol=(bass+mid+treb_att)*.3333;\n\nredsine=.5+.15*bass*sin(time*3);\ngreensine=.5+.15*mid*sin(time*2);\nbluesine=.5+.15*treb*sin(time);\n\nredif=if(above(bass,1.2),redsine,if(above(redif,.95),0,redif*.85));\ngreenif=if(above(mid,1.2),greensine,if(above(greenif,.95),0,greenif*.85));\nblueif=if(above(treb,1.2),bluesine,if(above(blueif,.95),0,blueif*.85));\n\nwave_r=redif;\nwave_g=greenif;\nwave_b=blueif;\n\nq11=sin(time)-1;\nq12=sin(time)-1;","pixel_eqs_eel":"dx=dx+.08*sin(x*32+sin(time*.51)*20*cos(time*.41));\ndy=dy+.08*sin(y*32+sin(time*.58)*20*cos(time*.33));","warp":" shader_body { \n  float n_1;\n  vec3 ret_2;\n  vec4 tmpvar_3;\n  tmpvar_3 = texture (sampler_pw_main, uv);\n  ret_2 = tmpvar_3.xyz;\n  n_1 = (clamp ((texture (sampler_pw_main, \n    (uv + texsize.zw)\n  ).x * 999.0), 0.0, 1.0) + clamp ((texture (sampler_pw_main, \n    (uv + (texsize.zw * vec2(1.0, 0.0)))\n  ).x * 999.0), 0.0, 1.0));\n  n_1 = (n_1 + clamp ((texture (sampler_pw_main, \n    (uv + (texsize.zw * vec2(1.0, -1.0)))\n  ).x * 999.0), 0.0, 1.0));\n  n_1 = (n_1 + clamp ((texture (sampler_pw_main, \n    (uv + (texsize.zw * vec2(0.0, 1.0)))\n  ).x * 999.0), 0.0, 1.0));\n  n_1 = (n_1 + clamp ((texture (sampler_pw_main, \n    (uv + (texsize.zw * vec2(0.0, -1.0)))\n  ).x * 999.0), 0.0, 1.0));\n  n_1 = (n_1 + clamp ((texture (sampler_pw_main, \n    (uv + (texsize.zw * vec2(-1.0, 1.0)))\n  ).x * 999.0), 0.0, 1.0));\n  n_1 = (n_1 + clamp ((texture (sampler_pw_main, \n    (uv + (texsize.zw * vec2(-1.0, 0.0)))\n  ).x * 999.0), 0.0, 1.0));\n  n_1 = (n_1 + clamp ((texture (sampler_pw_main, \n    (uv - texsize.zw)\n  ).x * 999.0), 0.0, 1.0));\n  if ((n_1 < 1.9)) {\n    ret_2 = (tmpvar_3.xyz - 0.4);\n  };\n  if ((n_1 > 3.1)) {\n    ret_2 = (ret_2 - 0.4);\n  };\n  bool tmpvar_4;\n  if ((ret_2.x < 0.1)) {\n    tmpvar_4 = (abs((n_1 - 3.0)) < 0.5);\n  } else {\n    tmpvar_4 = bool(0);\n  };\n  if (tmpvar_4) {\n    ret_2 = (ret_2 + 0.4);\n  };\n  vec4 tmpvar_5;\n  tmpvar_5.w = 1.0;\n  tmpvar_5.xyz = ret_2;\n  ret = tmpvar_5.xyz;\n }","comp":" shader_body { \n  vec2 uv_1;\n  vec3 ret_2;\n  uv_1 = (0.05 + (0.9 * uv));\n  ret_2 = (abs((\n    ((texture (sampler_blur3, (uv_1 + (0.01 * \n      ((bass + mid) + treb)\n    ))).xyz * scale3) + bias3)\n   - texture (sampler_main, uv_1).xyz)) * 6.0);\n  ret_2 = (ret_2 * 1.333);\n  vec4 tmpvar_3;\n  tmpvar_3.w = 1.0;\n  tmpvar_3.xyz = ret_2;\n  ret = tmpvar_3.xyz;\n }","warp_hlsl":"shader_body\n{\n  // sample previous frame\n  ret = tex2D( sampler_pw_main, uv ).xyz;\n\n  float n;\n  float2 d = texsize.zw*1;\n  n  = saturate(tex2D(sampler_pw_main, uv+d*float2( 1, 1)).x*999);\n  n += saturate(tex2D(sampler_pw_main, uv+d*float2( 1, 0)).x*999);\n  n += saturate(tex2D(sampler_pw_main, uv+d*float2( 1,-1)).x*999);\n  n += saturate(tex2D(sampler_pw_main, uv+d*float2( 0, 1)).x*999);\n  n += saturate(tex2D(sampler_pw_main, uv+d*float2( 0,-1)).x*999);\n  n += saturate(tex2D(sampler_pw_main, uv+d*float2(-1, 1)).x*999);\n  n += saturate(tex2D(sampler_pw_main, uv+d*float2(-1, 0)).x*999);\n  n += saturate(tex2D(sampler_pw_main, uv+d*float2(-1,-1)).x*999);\n  \nfloat t = 0.4;\n  if (n < 1.9)\n    ret -= t;\n  if (n > 3.1)\n    ret -= t;\n  if (ret.x < 0.1 && abs(n-3) < 0.5)\n    ret += t;\n\n  //ret *= saturate(6 - 19*(GetBlur1(uv_orig).x));\n  \n  //float dist_from_bar = abs(uv_orig.y - frac(time*0.23));\n  //ret *= saturate( 24*dist_from_bar - 0.5 );  \n\n  // darken (decay) over time\n  //ret = (ret - 0.016)*0.985;\n}","comp_hlsl":"\n\n\n\nshader_body\n{\n    uv = 0.05 + 0.9*uv;\n    ret = tex2D(sampler_main, uv).xyz;\n      // SUPER GLOW EDGES - looks awesome w/octopus\n      float3 avg_col = GetBlur3(uv+.01*(bass+mid+treb));\n      ret = abs(avg_col - ret)*6;\n    ret *= 1.333; // a little bit of overbright\n}"}