{"version":1,"baseVals":{"rating":5,"gammaadj":1,"decay":0.898999,"echo_zoom":0.999993,"wave_brighten":0,"wrap":0,"wave_a":0.001,"wave_scale":0.370543,"wave_smoothing":0.9,"wave_mystery":-0.18,"warpanimspeed":0.842832,"warpscale":0.132664,"zoomexp":5.995782,"zoom":0.999999,"warp":0.01,"wave_r":0,"wave_g":0,"wave_b":0,"ob_size":0.005,"ob_a":0.92,"ib_size":0,"ib_r":0,"ib_g":0,"ib_b":0,"mv_a":0},"shapes":[{"baseVals":{"enabled":1,"sides":100,"textured":1,"tex_ang":3.141593,"tex_zoom":1.0081,"r":0,"g2":0,"a2":1,"border_a":1},"init_eqs_str":"a.q2=0;a.q1=0;a.q8=0;","frame_eqs_str":"a.rad=2.6667*a.q2;a.r=1;a.g=a.r;a.b=a.r;a.r2=a.r;a.g2=a.g;a.b2=a.b;a.x=.5+(a.q1-a.q2)*Math.cos(a.q8);a.y=.5+1.333*(a.q1-a.q2)*Math.sin(a.q8);a.ang=.6*a.q8;","init_eqs_eel":"","frame_eqs_eel":"rad=q2*2.6667;\n\nr=1;g=r;b=r;r2=r;g2=g;b2=b;\n\nx=.5+(q1-q2)*cos(q8);\ny=.5+1.333*(q1-q2)*sin(q8);\n\nang=.6*q8;\n\n"},{"baseVals":{"enabled":1,"sides":100,"additive":1,"rad":0.496295,"tex_ang":1.570796,"tex_zoom":1.0081,"g":1,"b":1,"r2":0.3,"g2":0.3,"b2":0.6,"border_a":0},"init_eqs_str":"a.t=0;a.q6=0;","frame_eqs_str":"a.t=mod(a.frame,4);a.x=.1*below(a.t,2)+.9*above(a.t,1);a.y=.1*mod(a.t,2)+.9*(1-mod(a.t,2));a.a=pow(a.q6,20);","init_eqs_eel":"","frame_eqs_eel":"t=frame%4;\n\nx=below(t,2)*.1+above(t,1)*.9;\ny=(t%2)*.1+(1-t%2)*.9;\n\na=pow(q6,20);"},{"baseVals":{"enabled":0},"init_eqs_str":"","frame_eqs_str":"t=fram","init_eqs_eel":"","frame_eqs_eel":"t=fram"},{"baseVals":{"enabled":0},"init_eqs_str":"","frame_eqs_str":"t=fram","init_eqs_eel":"","frame_eqs_eel":"t=fram"}],"waves":[{"baseVals":{"enabled":1,"thick":1},"init_eqs_str":"a.sw6=0;a.sw2=0;a.sw3=0;a.sw5=0;a.q1=0;a.t8=0;a.d1=0;a.hue=0;a.h=0;a.sw1=0;a.rr=0;a.sw4=0;a.q8=0;","frame_eqs_str":"a.t8=1;","point_eqs_str":"a.x=a.q1*Math.cos(6.2831*a.sample);a.y=a.q1*Math.sin(6.2831*a.sample);a.x=a.x*a.t8+.5;a.y=a.y*a.t8*1.333+.5;a.hue=.1*a.q8+2*a.sample;a.h=6*(a.hue-Math.floor(a.hue));a.sw1=below(a.h,1);a.sw2=(1-a.sw1)*below(a.h,2);a.sw3=(1-a.sw1)*(1-a.sw2)*below(a.h,3);a.sw4=(1-a.sw1)*(1-a.sw2)*(1-a.sw3)*below(a.h,4);a.sw6=above(a.h,5);a.sw5=(1-a.sw1)*(1-a.sw2)*(1-a.sw3)*(1-a.sw4)*(1-a.sw6);a.r=a.sw1+a.sw2*(2-a.h)+a.sw5*(a.h-4)+a.sw6;a.g=a.sw1*a.h+a.sw2+a.sw3+a.sw4*(4-a.h);a.b=a.sw3*(a.h-2)+\na.sw4+a.sw5+a.sw6*(6-a.h);a.rr=.1;a.d1=below(a.sample,.025)+above(a.sample,.975);a.d1+=below(a.sample,.275)*above(a.sample,.225);a.d1+=below(a.sample,.525)*above(a.sample,.475);a.d1+=below(a.sample,.775)*above(a.sample,.725);a.r*=1-a.d1;a.g*=1-a.d1;a.b*=1-a.d1;","init_eqs_eel":"","frame_eqs_eel":"\nt8=1; // scale","point_eqs_eel":"x=q1*cos(6.2831*sample);\ny=q1*sin(6.2831*sample);\n\nx=x*t8+.5;\ny=y*t8*1.333+.5;\n\nhue=.1*q8+2*sample; // change this\nh=6*(hue-int(hue));\nsw1=below(h,1); sw2=(1-sw1)*below(h,2); sw3=(1-sw1)*(1-sw2)*below(h,3); sw4=(1-sw1)*(1-sw2)*(1-sw3)*below(h,4);\nsw6=above(h,5); sw5=(1-sw1)*(1-sw2)*(1-sw3)*(1-sw4)*(1-sw6);\nr=sw1+sw2*(2-h)+sw5*(h-4)+sw6;\ng=sw1*h+sw2+sw3+sw4*(4-h);\nb=sw3*(h-2)+sw4+sw5+sw6*(6-h);\n\nrr=.1;\nd1=below(sample,.025)+above(sample,.975);\nd1=d1+below(sample,.275)*above(sample,.225);\nd1=d1+below(sample,.525)*above(sample,.475);\nd1=d1+below(sample,.775)*above(sample,.725);\nr=(1-d1)*r;\ng=(1-d1)*g;\nb=(1-d1)*b;"},{"baseVals":{"enabled":1,"thick":1},"init_eqs_str":"a.n=0;a.sw6=0;a.sw2=0;a.t1=0;a.sw3=0;a.sw5=0;a.q1=0;a.t8=0;a.hue=0;a.t7=0;a.t2=0;a.q2=0;a.h=0;a.sw1=0;a.sw4=0;a.q8=0;","frame_eqs_str":"a.t1=(a.q1-a.q2)*Math.cos(a.q8);a.t2=(a.q1-a.q2)*Math.sin(a.q8);a.t8=1;a.t7=Math.min(.2+.8*Math.abs(Math.tan(div(a.q8,6.2831))),1);","point_eqs_str":"a.x=a.q2*Math.cos(6.2831*a.sample);a.y=a.q2*Math.sin(6.2831*a.sample);a.x+=a.t1;a.y+=a.t2;a.x=a.x*a.t8+.5;a.y=a.y*a.t8*1.333+.5;a.n=2;a.hue=.1*a.q8+a.n*a.sample+0*Math.cos(2*a.q8);a.h=6*(a.hue-Math.floor(a.hue));a.sw1=below(a.h,1);a.sw2=(1-a.sw1)*below(a.h,2);a.sw3=(1-a.sw1)*(1-a.sw2)*below(a.h,3);a.sw4=(1-a.sw1)*(1-a.sw2)*(1-a.sw3)*below(a.h,4);a.sw6=above(a.h,5);a.sw5=(1-a.sw1)*(1-a.sw2)*(1-a.sw3)*(1-a.sw4)*(1-a.sw6);a.r=a.sw1+a.sw2*(2-a.h)+a.sw5*(a.h-4)+a.sw6;a.g=a.sw1*a.h+\na.sw2+a.sw3+a.sw4*(4-a.h);a.b=a.sw3*(a.h-2)+a.sw4+a.sw5+a.sw6*(6-a.h);a.r*=a.t7;a.g*=a.t7;a.b*=a.t7;","init_eqs_eel":"","frame_eqs_eel":"t1=(q1-q2)*cos(q8);\nt2=(q1-q2)*sin(q8);\n\nt8=1; //  scale\n\nt7=min(.2+.8*abs(tan(q8/6.2831)),1);\n\n","point_eqs_eel":"x=q2*cos(6.2831*sample);\ny=q2*sin(6.2831*sample);\n\nx=x+t1;\ny=y+t2;\n\nx=x*t8+.5;\ny=y*t8*1.333+.5;\n\nn=2;\n\nhue=.1*q8+n*sample+0*cos(2*q8); // change this\nh=6*(hue-int(hue));\nsw1=below(h,1); sw2=(1-sw1)*below(h,2); sw3=(1-sw1)*(1-sw2)*below(h,3); sw4=(1-sw1)*(1-sw2)*(1-sw3)*below(h,4);\nsw6=above(h,5); sw5=(1-sw1)*(1-sw2)*(1-sw3)*(1-sw4)*(1-sw6);\nr=sw1+sw2*(2-h)+sw5*(h-4)+sw6;\ng=sw1*h+sw2+sw3+sw4*(4-h);\nb=sw3*(h-2)+sw4+sw5+sw6*(6-h);\nr=t7*r;\ng=t7*g;\nb=t7*b;"},{"baseVals":{"enabled":1,"thick":1,"additive":1,"smoothing":0},"init_eqs_str":"a.t1=0;","frame_eqs_str":"","point_eqs_str":"a.t1=below(a.sample,.5);a.a=below(a.sample,.47)+above(a.sample,.53);a.sample=2*a.t1*a.sample+2*(1-a.t1)*(a.sample-.5);a.x=.18*a.sample;a.y=.5+.2*(a.value1+a.value2);a.x=a.t1*(a.x+0)+(1-a.t1)*(a.x+.82);a.r=1;a.g=.2;a.b=0;","init_eqs_eel":"","frame_eqs_eel":"","point_eqs_eel":"t1=below(sample,.5);\na = below(sample,.47)+above(sample,.53);\nsample=t1*2*sample+(1-t1)*2*(sample-.5);\n\nx=sample*.18;\ny=.5+.2*(value1+value2);\n\nx=t1*(x+0)+(1-t1)*(x+.82);\n\nr=1;g=.2;b=0;"},{"baseVals":{"enabled":1,"thick":1,"additive":1,"smoothing":0},"init_eqs_str":"a.t1=0;a.t5=0;a.q8=0;","frame_eqs_str":"a.t5=-a.q8;","point_eqs_str":"a.t1=below(a.sample,.5);a.a=below(a.sample,.47)+above(a.sample,.53);a.sample=2*a.t1*a.sample+2*(1-a.t1)*(a.sample-.5);a.x=.5+.2*(a.value1+a.value2);a.y=.18*a.sample;a.y=a.t1*(a.y-.11)+(1-a.t1)*(a.y+.93);a.r=1;a.g=.2;a.b=0;","init_eqs_eel":"","frame_eqs_eel":"t5=-q8","point_eqs_eel":"t1=below(sample,.5);\na = below(sample,.47)+above(sample,.53);\nsample=t1*2*sample+(1-t1)*2*(sample-.5);\n\nx=.5+.2*(value1+value2);\ny=sample*.18;\n\ny=t1*(y-.11)+(1-t1)*(y+.93);\n\nr=1;g=.2;b=0;"}],"init_eqs_str":"a.addtime=0;a.pcontbass=0;a.q6=0;a.q1=0;a.mytime=0;a.coef=0;a.t=0;a.q2=0;a.contbass=0;a.q8=0;a.contbass=.7;","frame_eqs_str":"a.decay=.99;a.zoom=1;a.warp=0;a.coef=div(1,a.fps);a.contbass=(1-.1*a.coef)*a.contbass+.1*a.coef*a.bass;a.addtime=above(a.contbass-a.pcontbass,0);a.addtime=Math.min(10*a.addtime*(a.contbass-a.pcontbass)*a.fps,1);a.mytime+=div(1,a.fps)*(1+a.addtime);a.q1=.33141;a.q6=Math.min(div(a.contbass,1.2),1);a.q2=.139091+.18*a.q6;a.q8=a.mytime;a.pcontbass=a.contbass;a.monitor=a.contbass;a.zoom=1.002;a.monitor=a.q6;","pixel_eqs_str":"a.t=(below(a.x,.2)+above(a.x,.8))*below(Math.abs(a.y-.5),.1);a.t+=below(Math.abs(a.x-.5),.1)*(above(a.y,.9)+below(a.y,.1));a.warp=above(a.rad,.65)*below(a.rad,.75)*(1-a.t);","init_eqs_eel":"contbass=.7;","frame_eqs_eel":"decay=.99; zoom=1; warp=0;\n\ncoef=1/FPS;\ncontbass=(1-.1*coef)*contbass+.1*coef*bass;\naddtime=above(contbass-pcontbass,0);\naddtime=min(10*addtime*(contbass-pcontbass)*FPS,1);\nmytime=mytime+(1/FPS)*(1+addtime);\n\nq1=.34641-.015;\n\n\nq6=min(contbass/1.2,1);\nq2=.278182*.5+.18*q6;\n\nq8=mytime;\n\npcontbass=contbass;\nmonitor=contbass;\n\nzoom=1.002;\n\nmonitor=q6;","pixel_eqs_eel":"t=(below(x,.2)+above(x,.8))*below( abs(y-.5),.1);\nt=t+below( abs(x-.5),.1)*(above(y,.9)+below(y,.1));\n\nwarp=above(rad,.65)*below(rad,.75)*(1-t);","warp":"","comp":"","warp_hlsl":"","comp_hlsl":""}